{
	"passionProjects": [
		{
			"id": "suburbsolution",
			"title": "Suburb Solutions",
			"thumbnail": "path/to/suburbsolutions",
			"description": "Sophiscated and user-centric solutions that provides real estate data and analytics in Australia"
		},
		{
			"id": "dtpHome",
			"title": "Decentralized Trading Platform",
			"thumbnail": "path/to/dtp_home",
			"description": "Decentralized Trading Platform for user transactions"
		},
		{
			"id": "proproo",
			"title": "Proproo - Property Listing Platform",
			"thumbnail": "path/to/proproo",
			"description": "Proproo's website is the one of the biggest project that I personally have ever done myself especially for the database, backend and frontend"
		}

	]
}
